{
	"declarations": [
		{
			"op": "pointer/get"
		},
		{
			"op": "math/add"
		},
		{
			"op": "pointer/set"
		},
		{
			"op": "event/onStart"
		},
		{
			"op": "math/eq"
		},
		{
			"op": "variable/set"
		}
	],
	"nodes": [
		{
			"declaration": 0,
			"values": {},
			"configuration": {
				"pointer": {
					"value": [
						"/nodes/0/translation"
					]
				},
				"type": {
					"value": [
						"4"
					]
				}
			},
			"flows": {},
			"metadata": {
				"positionX": 238.0101951248315,
				"positionY": -190.3305218448665
			}
		},
		{
			"declaration": 1,
			"values": {
				"a": {
					"socket": "value",
					"node": 0
				},
				"b": {
					"value": [
						1,
						2,
						3
					],
					"type": "4",
					"typeOptions": [
						1,
						2,
						3,
						4,
						5,
						6
					]
				}
			},
			"configuration": {},
			"flows": {},
			"metadata": {
				"positionX": 662.8152863842106,
				"positionY": 210.77107438552645
			}
		},
		{
			"declaration": 4,
			"values": {
				"a": {
					"socket": "value",
					"node": 0
				},
				"b": {
					"value": [
						2,
						3,
						4
					],
					"type": "4",
					"typeOptions": [
						0,
						1,
						2,
						3,
						4,
						5,
						6
					]
				}
			},
			"configuration": {},
			"flows": {},
			"metadata": {
				"positionX": 1660.047791879354,
				"positionY": 185.99142410692696
			}
		},
		{
			"declaration": 3,
			"values": {},
			"configuration": {},
			"flows": {
				"out": {
					"node": 4,
					"socket": "in"
				}
			},
			"metadata": {
				"positionX": 664.0519793683188,
				"positionY": 506.8550353748245
			}
		},
		{
			"declaration": 2,
			"values": {
				"value": {
					"socket": "value",
					"node": 1
				}
			},
			"configuration": {
				"pointer": {
					"value": [
						"/nodes/0/translation"
					]
				},
				"type": {
					"value": [
						"4"
					]
				}
			},
			"flows": {
				"out": {
					"node": 5,
					"socket": "in"
				},
				"err": {}
			},
			"metadata": {
				"positionX": 1217.8713632005804,
				"positionY": 394.3330018343015
			}
		},
		{
			"declaration": 5,
			"values": {
				"value": {
					"socket": "value",
					"node": 2
				}
			},
			"configuration": {
				"variable": {
					"value": [
						"0"
					]
				}
			},
			"flows": {
				"out": {}
			},
			"metadata": {
				"positionX": 1998.4929708879583,
				"positionY": 453.2312537656692
			}
		}
	],
	"variables": [
		{
			"name": "TestPassed",
			"value": [
				false
			],
			"type": 0
		}
	],
	"events": [],
	"types": [
		{
			"name": "bool",
			"signature": "bool"
		},
		{
			"name": "int",
			"signature": "int"
		},
		{
			"name": "float",
			"signature": "float"
		},
		{
			"name": "float2",
			"signature": "float2"
		},
		{
			"name": "float3",
			"signature": "float3"
		},
		{
			"name": "float4",
			"signature": "float4"
		},
		{
			"name": "float4x4",
			"signature": "float4x4"
		},
		{
			"name": "AMZN_interactivity_string",
			"signature": "custom",
			"extensions": {
				"AMZN_interactivity_string": {}
			}
		}
	]
}